neuropacs/__init__.py
neuropacs/sdk.py
tests/__init__.py
tests/test_utils.py
tests/tests.py
neuropacs-1.8.6.dist-info/LICENSE
neuropacs-1.8.6.dist-info/METADATA
neuropacs-1.8.6.dist-info/WHEEL
neuropacs-1.8.6.dist-info/top_level.txt
neuropacs-1.8.6.dist-info/RECORD
