Metadata-Version: 2.1
Name: neuropacs
Version: 1.8.6
Summary: neuropacs Python API
Home-page: https://github.com/neuropacs/neuropacs-py-sdk
Author: Kerrick Cavanaugh
Author-email: kerrick@neuropacs.com
License: MIT
Platform: UNKNOWN
Classifier: Development Status :: 4 - Beta
Classifier: Intended Audience :: Healthcare Industry
Classifier: License :: OSI Approved :: MIT License
Classifier: Programming Language :: Python :: 3
License-File: LICENSE
Requires-Dist: cryptography>=41.0.1
Requires-Dist: pycryptodome>=3.20.0
Requires-Dist: requests>=2.31.0
Requires-Dist: requests-toolbelt>=1.0.0
Requires-Dist: dicomweb-client>=0.59.3
